models/__init__.py
models/custom.py
models/model_gen.py
models/training.py
reluble/__init__.py
reluble/checker.py
reluble/exceptions.py
reluble/predicate.py
reluble/warn.py
reluble/nn/__init__.py
reluble/nn/modules/__init__.py
reluble/nn/modules/activation.py
reluble/nn/modules/batchnorm.py
reluble/nn/modules/container.py
reluble/nn/modules/conv.py
reluble/nn/modules/corruption.py
reluble/nn/modules/dropout.py
reluble/nn/modules/flatten.py
reluble/nn/modules/linear.py
reluble/nn/modules/module.py
reluble/nn/modules/pooling.py
reluble/utils/__init__.py
reluble/utils/printing.py
reluble/utils/stats.py
reluble-0.1.0.dist-info/METADATA
reluble-0.1.0.dist-info/WHEEL
reluble-0.1.0.dist-info/top_level.txt
reluble-0.1.0.dist-info/RECORD
