Metadata-Version: 2.1
Name: reluble
Version: 0.1.0
Summary: Reliable deep network training, saving you hours.
Home-page: UNKNOWN
Author: Nathan Drenkow, Catalina Gomez, and Benjamin D. Killeen
Author-email: killeen@jhu.edu
License: UNKNOWN
Platform: UNKNOWN
Requires-Python: >=3.8
Requires-Dist: numpy
Requires-Dist: torch
Requires-Dist: termcolor
Requires-Dist: scipy
